fboauth2.py
setup.py
fboauth2.egg-info/PKG-INFO
fboauth2.egg-info/SOURCES.txt
fboauth2.egg-info/dependency_links.txt
fboauth2.egg-info/not-zip-safe
fboauth2.egg-info/requires.txt
fboauth2.egg-info/top_level.txt