Metadata-Version: 1.0
Name: fboauth2
Version: 0.1.0
Summary: Bare minimum Facebook OAuth2 client
Home-page: https://github.com/marksteve/fboauth2
Author: Mark Steve Samson
Author-email: hello@marksteve.com
License: MIT
Platform: any
Classifier: Development Status :: 4 - Beta
Classifier: Environment :: Web Environment
Classifier: Intended Audience :: Developers
Classifier: License :: OSI Approved :: MIT License
Classifier: Operating System :: OS Independent
Classifier: Programming Language :: Python :: 2 :: Only
Classifier: Topic :: Internet :: WWW/HTTP
Classifier: Topic :: Software Development :: Libraries
